fextract/__init__.py
fextract/cli.py
fextract/modules/__init__.py
fextract/modules/f_cmp.py
fextract/modules/f_ext.py
fextract-1.0.0.dist-info/licenses/LICENSE.txt
fextract-1.0.0.dist-info/METADATA
fextract-1.0.0.dist-info/WHEEL
fextract-1.0.0.dist-info/entry_points.txt
fextract-1.0.0.dist-info/top_level.txt
fextract-1.0.0.dist-info/RECORD
