Metadata-Version: 2.4
Name: fextract
Version: 1.0.0
Summary: Fast multithreaded file extraction and compression tool
Author-email: Emirhan Kayar <emirhan.kayar80@gmail.com>
License: MIT
Project-URL: Homepage, https://github.com/emirhankayar/fextract
Project-URL: BugReports, https://github.com/emirhankayar/fextract/issues
Project-URL: Source, https://github.com/emirhankayar/fextract
Keywords: zip,compression,extraction,multithreading,fast,archive
Classifier: Development Status :: 4 - Beta
Classifier: Intended Audience :: Developers
Classifier: License :: OSI Approved :: MIT License
Classifier: Programming Language :: Python :: 3
Classifier: Topic :: System :: Archiving
Classifier: Topic :: Utilities
Requires-Python: >=3.11
License-File: LICENSE.txt
Dynamic: license-file
